{
  "metadata": {
    "toolPackage": "@microsoft/api-extractor",
    "toolVersion": "7.33.4",
    "schemaVersion": 1010,
    "oldestForwardsCompatibleVersion": 1001,
    "tsdocConfig": {
      "$schema": "https://developer.microsoft.com/json-schemas/tsdoc/v0/tsdoc.schema.json",
      "noStandardTags": true,
      "tagDefinitions": [
        {
          "tagName": "@alpha",
          "syntaxKind": "modifier"
        },
        {
          "tagName": "@beta",
          "syntaxKind": "modifier"
        },
        {
          "tagName": "@defaultValue",
          "syntaxKind": "block"
        },
        {
          "tagName": "@decorator",
          "syntaxKind": "block",
          "allowMultiple": true
        },
        {
          "tagName": "@deprecated",
          "syntaxKind": "block"
        },
        {
          "tagName": "@eventProperty",
          "syntaxKind": "modifier"
        },
        {
          "tagName": "@example",
          "syntaxKind": "block",
          "allowMultiple": true
        },
        {
          "tagName": "@experimental",
          "syntaxKind": "modifier"
        },
        {
          "tagName": "@inheritDoc",
          "syntaxKind": "inline"
        },
        {
          "tagName": "@internal",
          "syntaxKind": "modifier"
        },
        {
          "tagName": "@label",
          "syntaxKind": "inline"
        },
        {
          "tagName": "@link",
          "syntaxKind": "inline",
          "allowMultiple": true
        },
        {
          "tagName": "@override",
          "syntaxKind": "modifier"
        },
        {
          "tagName": "@packageDocumentation",
          "syntaxKind": "modifier"
        },
        {
          "tagName": "@param",
          "syntaxKind": "block",
          "allowMultiple": true
        },
        {
          "tagName": "@privateRemarks",
          "syntaxKind": "block"
        },
        {
          "tagName": "@public",
          "syntaxKind": "modifier"
        },
        {
          "tagName": "@readonly",
          "syntaxKind": "modifier"
        },
        {
          "tagName": "@remarks",
          "syntaxKind": "block"
        },
        {
          "tagName": "@returns",
          "syntaxKind": "block"
        },
        {
          "tagName": "@sealed",
          "syntaxKind": "modifier"
        },
        {
          "tagName": "@see",
          "syntaxKind": "block"
        },
        {
          "tagName": "@throws",
          "syntaxKind": "block",
          "allowMultiple": true
        },
        {
          "tagName": "@typeParam",
          "syntaxKind": "block",
          "allowMultiple": true
        },
        {
          "tagName": "@virtual",
          "syntaxKind": "modifier"
        },
        {
          "tagName": "@betaDocumentation",
          "syntaxKind": "modifier"
        },
        {
          "tagName": "@internalRemarks",
          "syntaxKind": "block"
        },
        {
          "tagName": "@preapproved",
          "syntaxKind": "modifier"
        }
      ],
      "supportForTags": {
        "@alpha": true,
        "@beta": true,
        "@defaultValue": true,
        "@decorator": true,
        "@deprecated": true,
        "@eventProperty": true,
        "@example": true,
        "@experimental": true,
        "@inheritDoc": true,
        "@internal": true,
        "@label": true,
        "@link": true,
        "@override": true,
        "@packageDocumentation": true,
        "@param": true,
        "@privateRemarks": true,
        "@public": true,
        "@readonly": true,
        "@remarks": true,
        "@returns": true,
        "@sealed": true,
        "@see": true,
        "@throws": true,
        "@typeParam": true,
        "@virtual": true,
        "@betaDocumentation": true,
        "@internalRemarks": true,
        "@preapproved": true
      },
      "reportUnsupportedHtmlElements": false
    }
  },
  "kind": "Package",
  "canonicalReference": "@doonce/latex-svg-dataurl!",
  "docComment": "",
  "name": "@doonce/latex-svg-dataurl",
  "preserveMemberOrder": false,
  "members": [
    {
      "kind": "EntryPoint",
      "canonicalReference": "@doonce/latex-svg-dataurl!",
      "name": "",
      "preserveMemberOrder": false,
      "members": [
        {
          "kind": "Function",
          "canonicalReference": "@doonce/latex-svg-dataurl!transformLatexToSVGDataUrl:function(1)",
          "docComment": "/**\n * 将 latex 公式转为 svg dataurl\n *\n * @date 2023-03-28 19:27:07  @export\n *\n * @param latex - latex 公式字符串\n *\n * @param retryInterval - 重试间隔 默认500ms\n *\n * @param retryMaxCount - 重试最大次数 默认10\n *\n * @param outputType - 输出类型,默认 dataUrl\n *\n * @returns {Promise<TransformLatexToSVGDataUrlRet>} svg dataurl\n */\n",
          "excerptTokens": [
            {
              "kind": "Content",
              "text": "export declare function transformLatexToSVGDataUrl({ latex, retryInterval, retryMaxCount, outputType }?: "
            },
            {
              "kind": "Reference",
              "text": "TransformLatexToSVGDataUrlParams",
              "canonicalReference": "@doonce/latex-svg-dataurl!TransformLatexToSVGDataUrlParams:type"
            },
            {
              "kind": "Content",
              "text": "): "
            },
            {
              "kind": "Reference",
              "text": "Promise",
              "canonicalReference": "!Promise:interface"
            },
            {
              "kind": "Content",
              "text": "<"
            },
            {
              "kind": "Reference",
              "text": "TransformLatexToSVGDataUrlRet",
              "canonicalReference": "@doonce/latex-svg-dataurl!TransformLatexToSVGDataUrlRet:type"
            },
            {
              "kind": "Content",
              "text": " | string>"
            },
            {
              "kind": "Content",
              "text": ";"
            }
          ],
          "fileUrlPath": "src/latex-svg-dataurl.ts",
          "returnTypeTokenRange": {
            "startIndex": 3,
            "endIndex": 7
          },
          "releaseTag": "Public",
          "overloadIndex": 1,
          "parameters": [
            {
              "parameterName": "{ latex, retryInterval, retryMaxCount, outputType }",
              "parameterTypeTokenRange": {
                "startIndex": 1,
                "endIndex": 2
              },
              "isOptional": true
            }
          ],
          "name": "transformLatexToSVGDataUrl"
        },
        {
          "kind": "TypeAlias",
          "canonicalReference": "@doonce/latex-svg-dataurl!TransformLatexToSVGDataUrlParams:type",
          "docComment": "",
          "excerptTokens": [
            {
              "kind": "Content",
              "text": "export declare type TransformLatexToSVGDataUrlParams = "
            },
            {
              "kind": "Content",
              "text": "{\n    latex: string; /** latex输入字符串 */\n    retryInterval?: number; /** 渲染失败的重试间隔,默认500ms */\n    retryMaxCount?: number; /** 渲染重试次数,默认10次 */\n    outputType: 'dataUrl' | 'svgStr' | 'both'; /** 输出类型,dataurl svgel 转换的string 或 都输出;默认 dataurl*/\n}"
            },
            {
              "kind": "Content",
              "text": ";"
            }
          ],
          "fileUrlPath": "src/latex-svg-dataurl.ts",
          "releaseTag": "Public",
          "name": "TransformLatexToSVGDataUrlParams",
          "typeTokenRange": {
            "startIndex": 1,
            "endIndex": 2
          }
        },
        {
          "kind": "TypeAlias",
          "canonicalReference": "@doonce/latex-svg-dataurl!TransformLatexToSVGDataUrlRet:type",
          "docComment": "",
          "excerptTokens": [
            {
              "kind": "Content",
              "text": "export declare type TransformLatexToSVGDataUrlRet = "
            },
            {
              "kind": "Content",
              "text": "{\n    dataUrl: string;\n    svgStr: string;\n}"
            },
            {
              "kind": "Content",
              "text": ";"
            }
          ],
          "fileUrlPath": "src/latex-svg-dataurl.ts",
          "releaseTag": "Public",
          "name": "TransformLatexToSVGDataUrlRet",
          "typeTokenRange": {
            "startIndex": 1,
            "endIndex": 2
          }
        },
        {
          "kind": "Function",
          "canonicalReference": "@doonce/latex-svg-dataurl!transformSvgEl2DataUrl:function(1)",
          "docComment": "/**\n * 将 svg 元素内容转为 dataurl\n *\n * @date 2023-03-28 17:34:57  @export\n *\n * @param svgEl - \n *\n * @returns {string} dataurl\n */\n",
          "excerptTokens": [
            {
              "kind": "Content",
              "text": "export declare function transformSvgEl2DataUrl(svgEl: "
            },
            {
              "kind": "Reference",
              "text": "SVGElement",
              "canonicalReference": "!SVGElement:interface"
            },
            {
              "kind": "Content",
              "text": "): "
            },
            {
              "kind": "Content",
              "text": "string"
            },
            {
              "kind": "Content",
              "text": ";"
            }
          ],
          "fileUrlPath": "src/latex-svg-dataurl.ts",
          "returnTypeTokenRange": {
            "startIndex": 3,
            "endIndex": 4
          },
          "releaseTag": "Public",
          "overloadIndex": 1,
          "parameters": [
            {
              "parameterName": "svgEl",
              "parameterTypeTokenRange": {
                "startIndex": 1,
                "endIndex": 2
              },
              "isOptional": false
            }
          ],
          "name": "transformSvgEl2DataUrl"
        }
      ]
    }
  ]
}
